flybrains/__init__.py
flybrains/__version__.py
flybrains/converters.py
flybrains/core.py
flybrains/download.py
flybrains/templates.py
flybrains/data/Aedes_mirror_landmarks_nm.csv
flybrains/data/BANC_mirror_landmarks_nm.csv
flybrains/data/FAFB14_maleCNS_landmarks.csv
flybrains/data/FAFB14_mirror_landmarks.csv
flybrains/data/FAFB14_symmetrize_landmarks_nm.csv
flybrains/data/FANC_mirror_landmarks.csv
flybrains/data/FLYWIRE_maleCNS_landmarks.csv
flybrains/data/FLYWIRE_mirror_landmarks.csv
flybrains/data/FLYWIRE_symmetrize_landmarks_nm.csv
flybrains/data/JRCFIB2022M_plotting_landmarks.csv
flybrains/data/MANC_FANC_landmarks_nm.csv
flybrains/data/lm-em-landmarks_v14.csv
flybrains/data/maleCNS_BANC_landmarks_nm.csv
flybrains/data/maleCNS_mirror_landmarks_nm.csv
flybrains/data/template_meta.json
flybrains/data/BANC_JRC2018F/0_manual_affine.txt
flybrains/data/BANC_JRC2018F/1_elastix_affine.txt
flybrains/data/BANC_JRC2018F/2_elastix_Bspline_coarse.txt
flybrains/data/BANC_JRC2018F/3_elastix_Bspline_fine.txt
flybrains/data/BANC_JRC2018F/BANC_to_template.txt
flybrains/data/BANC_JRC2018F/template_to_BANC.txt
flybrains/data/BANC_JRCVNC2018F/0_manual_affine.txt
flybrains/data/BANC_JRCVNC2018F/1_elastix_affine.txt
flybrains/data/BANC_JRCVNC2018F/2_elastix_Bspline_coarse.txt
flybrains/data/BANC_JRCVNC2018F/3_elastix_Bspline_fine.txt
flybrains/data/BANC_JRCVNC2018F/BANC_to_template.txt
flybrains/data/BANC_JRCVNC2018F/template_to_BANC.txt
flybrains/data/FANC_JRCVNC2018F/TransformParameters.FixedFANC.txt
flybrains/data/FANC_JRCVNC2018F/TransformParameters.FixedTemplate.Bspline.txt
flybrains/data/FANC_JRCVNC2018F/TransformParameters.FixedTemplate.affine.txt
flybrains/meshes/AEDES.ply
flybrains/meshes/BANC_brain.ply
flybrains/meshes/BANC_vnc.ply
flybrains/meshes/BANC_whole_brain.ply
flybrains/meshes/COURT2018VNS.ply
flybrains/meshes/Dmel-L1-CNS-Seymour.ply
flybrains/meshes/Dmel.ply
flybrains/meshes/DsecI.ply
flybrains/meshes/Dsim.ply
flybrains/meshes/Dvir.ply
flybrains/meshes/FAFB14.ply
flybrains-0.6.3.dist-info/licenses/LICENSE
flybrains-0.6.3.dist-info/METADATA
flybrains-0.6.3.dist-info/WHEEL
flybrains-0.6.3.dist-info/top_level.txt
flybrains-0.6.3.dist-info/RECORD
