Metadata-Version: 2.4
Name: flybrains
Version: 0.6.3
Summary: Transforms to map between different Drosophila template brains
Home-page: https://github.com/schlegelp/navis-flybrains
Author: Philipp Schlegel
Author-email: pms70@cam.ac.uk
License: GNU GPL V3
Keywords: Drosophila template registration brain navis transform
Classifier: Development Status :: 3 - Alpha
Classifier: Intended Audience :: Science/Research
Classifier: Topic :: Scientific/Engineering :: Bio-Informatics
Classifier: License :: OSI Approved :: GNU General Public License v3 or later (GPLv3+)
Classifier: Programming Language :: Python :: 3
Classifier: Programming Language :: Python :: 3.6
Classifier: Programming Language :: Python :: 3.7
Requires-Python: >=3.6
License-File: LICENSE
Requires-Dist: gitpython
Requires-Dist: navis>=0.6.0
Requires-Dist: numpy
Requires-Dist: pandas
Requires-Dist: h5py<=3.12.1
Provides-Extra: extras
Dynamic: author
Dynamic: author-email
Dynamic: classifier
Dynamic: description
Dynamic: description-content-type
Dynamic: home-page
Dynamic: keywords
Dynamic: license
Dynamic: license-file
Dynamic: provides-extra
Dynamic: requires-dist
Dynamic: requires-python
Dynamic: summary
